BiasBuster/__init__.py
BiasBuster/abroca.py
BiasBuster/equal_opportunity.py
BiasBuster/predictive_equality.py
BiasBuster/predictive_parity.py
BiasBuster-0.0.4.dist-info/LICENSE.txt
BiasBuster-0.0.4.dist-info/METADATA
BiasBuster-0.0.4.dist-info/WHEEL
BiasBuster-0.0.4.dist-info/top_level.txt
BiasBuster-0.0.4.dist-info/RECORD
