Metadata-Version: 2.1
Name: BiasBuster
Version: 0.0.4
Summary: A Python package to check for algorithmic bias.
Home-page: https://github.com/nathalierze/BiasBuster
Author: Nathalie Rzepka
Project-URL: Bug Tracker, https://github.com/nathalierze/BiasBuster/issuesL
Classifier: Programming Language :: Python :: 3
Classifier: License :: OSI Approved :: MIT License
Classifier: Operating System :: OS Independent
Requires-Python: >=3.6
License-File: LICENSE.txt
